{
  "user": "RanuK12",
  "generated_at": "2026-05-20T05:41:54.930Z",
  "stats": {
    "public_repos": 30,
    "total_stars": 1,
    "languages_count": 13,
    "last_push": "2026-05-19T05:41:18Z"
  },
  "languages": [
    {
      "name": "Python",
      "bytes": 66569103,
      "pct": 90.8
    },
    {
      "name": "Jupyter Notebook",
      "bytes": 2757385,
      "pct": 3.8
    },
    {
      "name": "JavaScript",
      "bytes": 1153301,
      "pct": 1.6
    },
    {
      "name": "HTML",
      "bytes": 1144657,
      "pct": 1.6
    },
    {
      "name": "TypeScript",
      "bytes": 1125111,
      "pct": 1.5
    },
    {
      "name": "CSS",
      "bytes": 313591,
      "pct": 0.4
    },
    {
      "name": "PowerShell",
      "bytes": 218880,
      "pct": 0.3
    },
    {
      "name": "Shell",
      "bytes": 38367,
      "pct": 0.1
    },
    {
      "name": "Batchfile",
      "bytes": 17399,
      "pct": 0
    },
    {
      "name": "PLpgSQL",
      "bytes": 6454,
      "pct": 0
    },
    {
      "name": "Dockerfile",
      "bytes": 4986,
      "pct": 0
    },
    {
      "name": "Java",
      "bytes": 1925,
      "pct": 0
    }
  ],
  "featured": [
    {
      "name": "cryptocurrency-price-monitor",
      "full_name": "RanuK12/cryptocurrency-price-monitor",
      "description": null,
      "url": "https://github.com/RanuK12/cryptocurrency-price-monitor",
      "homepage": null,
      "language": "Python",
      "stars": 1,
      "forks": 0,
      "topics": [],
      "updated": "2025-06-13T15:47:19Z"
    },
    {
      "name": "skills-copilot-codespaces-vscode",
      "full_name": "RanuK12/skills-copilot-codespaces-vscode",
      "description": "My clone repository",
      "url": "https://github.com/RanuK12/skills-copilot-codespaces-vscode",
      "homepage": null,
      "language": null,
      "stars": 0,
      "forks": 0,
      "topics": [],
      "updated": "2026-04-21T17:28:43Z"
    },
    {
      "name": "Ranuk.dev",
      "full_name": "RanuK12/Ranuk.dev",
      "description": null,
      "url": "https://github.com/RanuK12/Ranuk.dev",
      "homepage": null,
      "language": "JavaScript",
      "stars": 0,
      "forks": 0,
      "topics": [],
      "updated": "2026-05-19T05:41:18Z"
    },
    {
      "name": "Content-Creators-AI",
      "full_name": "RanuK12/Content-Creators-AI",
      "description": null,
      "url": "https://github.com/RanuK12/Content-Creators-AI",
      "homepage": null,
      "language": "Python",
      "stars": 0,
      "forks": 0,
      "topics": [],
      "updated": "2026-05-18T23:11:18Z"
    },
    {
      "name": "GARYCIO_Project",
      "full_name": "RanuK12/GARYCIO_Project",
      "description": null,
      "url": "https://github.com/RanuK12/GARYCIO_Project",
      "homepage": null,
      "language": "TypeScript",
      "stars": 0,
      "forks": 0,
      "topics": [],
      "updated": "2026-05-18T19:53:06Z"
    },
    {
      "name": "JobFinder",
      "full_name": "RanuK12/JobFinder",
      "description": null,
      "url": "https://github.com/RanuK12/JobFinder",
      "homepage": null,
      "language": "HTML",
      "stars": 0,
      "forks": 0,
      "topics": [],
      "updated": "2026-05-18T16:20:29Z"
    }
  ]
}
